aioresonate/__init__.py
aioresonate/cli.py
aioresonate/cli_audio.py
aioresonate/py.typed
aioresonate/client/__init__.py
aioresonate/client/client.py
aioresonate/client/time_sync.py
aioresonate/models/__init__.py
aioresonate/models/controller.py
aioresonate/models/core.py
aioresonate/models/metadata.py
aioresonate/models/player.py
aioresonate/models/types.py
aioresonate/models/visualizer.py
aioresonate/server/__init__.py
aioresonate/server/client.py
aioresonate/server/controller.py
aioresonate/server/events.py
aioresonate/server/group.py
aioresonate/server/metadata.py
aioresonate/server/player.py
aioresonate/server/server.py
aioresonate/server/stream.py
aioresonate/server/visualizer.py
aioresonate-0.13.1.dist-info/licenses/LICENSE
aioresonate-0.13.1.dist-info/METADATA
aioresonate-0.13.1.dist-info/WHEEL
aioresonate-0.13.1.dist-info/entry_points.txt
aioresonate-0.13.1.dist-info/top_level.txt
aioresonate-0.13.1.dist-info/RECORD
