Metadata-Version: 2.4
Name: aioresonate
Version: 0.13.1
Summary: Async Python implementation of the Resonate Protocol.
Author-email: The Resonate Protocol Authors <resonate@openhomefoundation.org>
License: Apache-2.0
Classifier: Environment :: Console
Classifier: Programming Language :: Python :: 3.12
Classifier: Programming Language :: Python :: 3.13
Requires-Python: >=3.12
License-File: LICENSE
Requires-Dist: aiohttp>=3.9.2
Requires-Dist: av>=15.0.0
Requires-Dist: mashumaro>=3.14
Requires-Dist: orjson>=3.10.0
Requires-Dist: pillow>=11.0.0
Requires-Dist: zeroconf>=0.147
Provides-Extra: cli
Requires-Dist: aioconsole>=0.8.0; extra == "cli"
Requires-Dist: sounddevice>=0.4.6; extra == "cli"
Provides-Extra: test
Requires-Dist: codespell==2.4.1; extra == "test"
Requires-Dist: isort==7.0.0; extra == "test"
Requires-Dist: mypy==1.18.2; extra == "test"
Requires-Dist: pre-commit==4.4.0; extra == "test"
Requires-Dist: pre-commit-hooks==6.0.0; extra == "test"
Requires-Dist: pytest==9.0.0; extra == "test"
Requires-Dist: pytest-aiohttp==1.1.0; extra == "test"
Requires-Dist: pytest-cov==7.0.0; extra == "test"
Requires-Dist: syrupy==5.0.0; extra == "test"
Requires-Dist: tomli==2.3.0; extra == "test"
Requires-Dist: ruff==0.14.4; extra == "test"
Dynamic: license-file
